kedro/__init__.py
kedro/__main__.py
kedro/logging.py
kedro/py.typed
kedro/utils.py
kedro/config/__init__.py
kedro/config/abstract_config.py
kedro/config/omegaconf_config.py
kedro/framework/__init__.py
kedro/framework/startup.py
kedro/framework/cli/__init__.py
kedro/framework/cli/catalog.py
kedro/framework/cli/cli.py
kedro/framework/cli/jupyter.py
kedro/framework/cli/pipeline.py
kedro/framework/cli/project.py
kedro/framework/cli/registry.py
kedro/framework/cli/starters.py
kedro/framework/cli/utils.py
kedro/framework/cli/hooks/__init__.py
kedro/framework/cli/hooks/manager.py
kedro/framework/cli/hooks/markers.py
kedro/framework/cli/hooks/specs.py
kedro/framework/context/__init__.py
kedro/framework/context/catalog_mixins.py
kedro/framework/context/context.py
kedro/framework/hooks/__init__.py
kedro/framework/hooks/manager.py
kedro/framework/hooks/markers.py
kedro/framework/hooks/specs.py
kedro/framework/project/__init__.py
kedro/framework/project/default_logging.yml
kedro/framework/project/rich_logging.yml
kedro/framework/session/__init__.py
kedro/framework/session/session.py
kedro/framework/session/store.py
kedro/io/__init__.py
kedro/io/cached_dataset.py
kedro/io/catalog_config_resolver.py
kedro/io/core.py
kedro/io/data_catalog.py
kedro/io/memory_dataset.py
kedro/io/shared_memory_dataset.py
kedro/ipython/__init__.py
kedro/ipython/logo-32x32.png
kedro/ipython/logo-64x64.png
kedro/ipython/logo-svg.svg
kedro/pipeline/__init__.py
kedro/pipeline/node.py
kedro/pipeline/pipeline.py
kedro/pipeline/transcoding.py
kedro/runner/__init__.py
kedro/runner/parallel_runner.py
kedro/runner/runner.py
kedro/runner/sequential_runner.py
kedro/runner/task.py
kedro/runner/thread_runner.py
kedro/templates/pipeline/cookiecutter.json
kedro/templates/pipeline/{{ cookiecutter.pipeline_name }}/__init__.py
kedro/templates/pipeline/{{ cookiecutter.pipeline_name }}/nodes.py
kedro/templates/pipeline/{{ cookiecutter.pipeline_name }}/pipeline.py
kedro-1.0.0.dist-info/licenses/LICENSE.md
kedro-1.0.0.dist-info/METADATA
kedro-1.0.0.dist-info/WHEEL
kedro-1.0.0.dist-info/entry_points.txt
kedro-1.0.0.dist-info/top_level.txt
kedro-1.0.0.dist-info/RECORD
