Metadata-Version: 2.4
Name: kedro
Version: 1.0.0
Summary: Kedro helps you build production-ready data and analytics pipelines
Author: Kedro
License: Apache Software License (Apache 2.0)
Project-URL: Homepage, https://kedro.org
Project-URL: Source, https://github.com/kedro-org/kedro
Project-URL: Documentation, https://docs.kedro.org
Project-URL: Tracker, https://github.com/kedro-org/kedro/issues
Keywords: pipelines,machine learning,data pipelines,data science,data engineering
Classifier: Development Status :: 5 - Production/Stable
Classifier: Programming Language :: Python :: 3.9
Classifier: Programming Language :: Python :: 3.10
Classifier: Programming Language :: Python :: 3.11
Classifier: Programming Language :: Python :: 3.12
Classifier: Programming Language :: Python :: 3.13
Requires-Python: >=3.9
License-File: LICENSE.md
Requires-Dist: attrs>=21.3
Requires-Dist: build>=0.7.0
Requires-Dist: cachetools>=4.1
Requires-Dist: click<8.2.0,>=4.0
Requires-Dist: cookiecutter<3.0,>=2.1.1
Requires-Dist: dynaconf<4.0,>=3.1.2
Requires-Dist: fsspec>=2021.4
Requires-Dist: gitpython>=3.0
Requires-Dist: importlib_resources<7.0,>=1.3
Requires-Dist: importlib-metadata<9.0,>=3.6
Requires-Dist: importlib_resources<7.0,>=1.3
Requires-Dist: kedro-telemetry>=0.5.0
Requires-Dist: more_itertools>=8.14.0
Requires-Dist: omegaconf>=2.1.1
Requires-Dist: parse>=1.19.0
Requires-Dist: pluggy>=1.0
Requires-Dist: PyYAML<7.0,>=4.2
Requires-Dist: rich<15.0,>=12.0
Requires-Dist: toml>=0.10.0
Requires-Dist: typing_extensions>=4.0
Provides-Extra: test
Requires-Dist: behave==1.2.6; extra == "test"
Requires-Dist: coverage[toml]; extra == "test"
Requires-Dist: detect-secrets~=1.5.0; extra == "test"
Requires-Dist: import-linter==2.3; extra == "test"
Requires-Dist: ipylab>=1.0.0; extra == "test"
Requires-Dist: ipython~=8.10; extra == "test"
Requires-Dist: jupyterlab_server>=2.11.1; extra == "test"
Requires-Dist: jupyterlab<5,>=3; extra == "test"
Requires-Dist: jupyter~=1.0; extra == "test"
Requires-Dist: kedro-datasets; extra == "test"
Requires-Dist: mypy~=1.0; extra == "test"
Requires-Dist: pandas~=2.0; extra == "test"
Requires-Dist: pluggy>=1.0; extra == "test"
Requires-Dist: pre-commit<5.0,>=2.9.2; extra == "test"
Requires-Dist: pytest-cov<7,>=3; extra == "test"
Requires-Dist: pytest-mock<4.0,>=1.7.1; extra == "test"
Requires-Dist: pytest-xdist[psutil]~=2.2.1; extra == "test"
Requires-Dist: pytest<9.0,>=7.2; extra == "test"
Requires-Dist: s3fs<2025.6,>=2021.4; extra == "test"
Requires-Dist: requests_mock; extra == "test"
Requires-Dist: pandas-stubs; extra == "test"
Requires-Dist: types-PyYAML; extra == "test"
Requires-Dist: types-cachetools; extra == "test"
Requires-Dist: types-requests; extra == "test"
Requires-Dist: types-toml; extra == "test"
Provides-Extra: docs
Requires-Dist: mkdocs>=1.6.1; extra == "docs"
Requires-Dist: mkdocs-material>=9.6.11; extra == "docs"
Requires-Dist: mkdocs-material-extensions>=1.3.1; extra == "docs"
Requires-Dist: mkdocs-mermaid2-plugin>=1.2.1; extra == "docs"
Requires-Dist: mkdocs-autorefs>=1.4.1; extra == "docs"
Requires-Dist: mkdocs-get-deps>=0.2.0; extra == "docs"
Requires-Dist: mkdocstrings>=0.29.1; extra == "docs"
Requires-Dist: mkdocstrings-python>=0.29.1; extra == "docs"
Requires-Dist: mkdocs-click; extra == "docs"
Requires-Dist: griffe; extra == "docs"
Provides-Extra: jupyter
Requires-Dist: ipylab>=1.0.0; extra == "jupyter"
Requires-Dist: notebook>=7.0.0; extra == "jupyter"
Provides-Extra: benchmark
Requires-Dist: asv; extra == "benchmark"
Provides-Extra: all
Requires-Dist: kedro[benchmark,docs,jupyter,test]; extra == "all"
Dynamic: license-file
